setup.py
distributions4rupali/Binomialdistribution.py
distributions4rupali/Gaussiandistribution.py
distributions4rupali/Generaldistribution.py
distributions4rupali/__init__.py
distributions4rupali.egg-info/PKG-INFO
distributions4rupali.egg-info/SOURCES.txt
distributions4rupali.egg-info/dependency_links.txt
distributions4rupali.egg-info/not-zip-safe
distributions4rupali.egg-info/top_level.txt