Metadata-Version: 1.0
Name: distributions4rupali
Version: 1.1
Summary: Gaussian and Binomial distributions
Home-page: UNKNOWN
Author: Rupali Sinha
Author-email: UNKNOWN
License: UNKNOWN
Platform: UNKNOWN
